talondoc/__init__.py
talondoc/__main__.py
talondoc/_version.py
talondoc/_autogen/__init__.py
talondoc/_autogen/resources/conf.py.jinja2
talondoc/_autogen/resources/index.md.jinja2
talondoc/_autogen/resources/index.rst.jinja2
talondoc/_autogen/resources/python_file.md.jinja2
talondoc/_autogen/resources/python_file.rst.jinja2
talondoc/_autogen/resources/talon_file.md.jinja2
talondoc/_autogen/resources/talon_file.rst.jinja2
talondoc/_cache_builtin/__init__.py
talondoc/_cache_builtin/resources/talon.json
talondoc/_util/__init__.py
talondoc/_util/builtin.py
talondoc/_util/io.py
talondoc/_util/logging.py
talondoc/_util/progress_bar.py
talondoc/analysis/__init__.py
talondoc/analysis/live/__init__.py
talondoc/analysis/live/resources/get_actions.py
talondoc/analysis/live/resources/get_captures.py
talondoc/analysis/live/resources/get_commands.py
talondoc/analysis/live/resources/get_lists.py
talondoc/analysis/live/resources/get_modes.py
talondoc/analysis/live/resources/get_settings.py
talondoc/analysis/live/resources/get_tags.py
talondoc/analysis/live/resources/get_version.py
talondoc/analysis/registry/__init__.py
talondoc/analysis/registry/data/__init__.py
talondoc/analysis/registry/data/abc.py
talondoc/analysis/registry/data/serialise.py
talondoc/analysis/static/__init__.py
talondoc/analysis/static/talon.py
talondoc/analysis/static/python/__init__.py
talondoc/analysis/static/python/shims.py
talondoc/description/__init__.py
talondoc/description/describer.py
talondoc/sphinx/__init__.py
talondoc/sphinx/domains.py
talondoc/sphinx/typing.py
talondoc/sphinx/_util/typing.py
talondoc/sphinx/_util/addnodes/__init__.py
talondoc/sphinx/_util/addnodes/fragtable.py
talondoc/sphinx/_util/addnodes/rule.py
talondoc/sphinx/directives/__init__.py
talondoc/sphinx/directives/action.py
talondoc/sphinx/directives/capture.py
talondoc/sphinx/directives/errors.py
talondoc/sphinx/directives/list.py
talondoc/sphinx/directives/mode.py
talondoc/sphinx/directives/setting.py
talondoc-1.0.0.dist-info/METADATA
talondoc-1.0.0.dist-info/WHEEL
talondoc-1.0.0.dist-info/entry_points.txt
talondoc-1.0.0.dist-info/top_level.txt
talondoc-1.0.0.dist-info/RECORD
